jinxed/__init__.py
jinxed/_keys.py
jinxed/_terminal.py
jinxed/_tparm.py
jinxed/_util.py
jinxed/has_key.py
jinxed/win32.py
jinxed/terminfo/__init__.py
jinxed/terminfo/ansicon.py
jinxed/terminfo/vtwin10.py
jinxed/terminfo/xterm.py
jinxed/terminfo/xterm_256color.py
jinxed-1.2.1.dist-info/LICENSE
jinxed-1.2.1.dist-info/METADATA
jinxed-1.2.1.dist-info/WHEEL
jinxed-1.2.1.dist-info/top_level.txt
jinxed-1.2.1.dist-info/RECORD
