Metadata-Version: 2.1
Name: jinxed
Version: 1.2.1
Summary: Jinxed Terminal Library
Home-page: https://github.com/Rockhopper-Technologies/jinxed
Author: Avram Lubkin
Author-email: avylove@rockhopper.net
Maintainer: Avram Lubkin
Maintainer-email: avylove@rockhopper.net
License: MPLv2.0
Keywords: terminal console blessed curses
Classifier: Development Status :: 5 - Production/Stable
Classifier: Environment :: Console
Classifier: Intended Audience :: Developers
Classifier: License :: OSI Approved :: Mozilla Public License 2.0 (MPL 2.0)
Classifier: Operating System :: POSIX
Classifier: Operating System :: Microsoft :: Windows
Classifier: Programming Language :: Python
Classifier: Programming Language :: Python :: 2.7
Classifier: Programming Language :: Python :: 3.5
Classifier: Programming Language :: Python :: 3.6
Classifier: Programming Language :: Python :: 3.7
Classifier: Programming Language :: Python :: 3.8
Classifier: Programming Language :: Python :: 3.9
Classifier: Programming Language :: Python :: 3.10
Classifier: Programming Language :: Python :: 3.11
Classifier: Programming Language :: Python :: 3.12
Classifier: Programming Language :: Python :: 3.13
Classifier: Programming Language :: Python :: Implementation :: CPython
Classifier: Programming Language :: Python :: Implementation :: PyPy
Classifier: Topic :: Terminals
License-File: LICENSE
Requires-Dist: ansicon; platform_system == "Windows"
